sitemap_gazer/__init__.py
sitemap_gazer/__main__.py
sitemap_gazer/batch/readme.py
sitemap_gazer/core/crawl.py
sitemap_gazer/core/diff.py
sitemap_gazer/core/init.py
sitemap_gazer/core/readme.py
sitemap_gazer/models.py
sitemap_gazer/utils.py
sitemap_gazer-0.0.2.dist-info/METADATA
sitemap_gazer-0.0.2.dist-info/WHEEL
sitemap_gazer-0.0.2.dist-info/entry_points.txt
sitemap_gazer-0.0.2.dist-info/RECORD
